dcsr/__init__.py
dcsr/orchestrator.py
dcsr/addons/__init__.py
dcsr/addons/loader.py
dcsr/agents/__init__.py
dcsr/agents/action_agent.py
dcsr/agents/base_agent.py
dcsr/agents/language_agent.py
dcsr/agents/logic_agent.py
dcsr/agents/perception_agent.py
dcsr-0.1.dist-info/METADATA
dcsr-0.1.dist-info/WHEEL
dcsr-0.1.dist-info/top_level.txt
dcsr-0.1.dist-info/RECORD
